<?xml version="1.0" encoding="UTF-8"?>
<sml:PhysicalSystem xmlns:sml="http://www.opengis.net/sensorml/2.0" xmlns:gco="http://www.isotc211.org/2005/gco" xmlns:gmd="http://www.isotc211.org/2005/gmd" xmlns:gml="http://www.opengis.net/gml/3.2" xmlns:swe="http://www.opengis.net/swe/2.0" xmlns:xlink="http://www.w3.org/1999/xlink" xmlns:xsi="http://www.w3.org/2001/XMLSchema-instance" gml:id="top" xsi:schemaLocation="http://www.opengis.net/sensorml/2.0 http://schemas.opengis.net/sensorML/2.0/sensorML.xsd">
    
      
       <gml:metaDataProperty>
        <gml:GenericMetaData>
            <gmd:CI_ResponsibleParty>
           
				<gmd:individualName>
                    <gco:CharacterString>Ivo Bernardo</gco:CharacterString>
                </gmd:individualName>
                 
                <gmd:organisationName>
                    <gco:CharacterString>YELLOW PAGES - EMSO</gco:CharacterString>
                </gmd:organisationName>
                <gmd:contactInfo>
                    <gmd:CI_Contact>
                    
                        <gmd:address>
                            <gmd:CI_Address>
                                <gmd:electronicMailAddress>
<gco:CharacterString>imbernardo@fc.ul.pt</gco:CharacterString>
                                </gmd:electronicMailAddress>
                            </gmd:CI_Address>
                        </gmd:address>
                        
                        <gmd:onlineResource>
                            <gmd:CI_OnlineResource>
                                <gmd:linkage>
<gmd:URL>http://www.esonetyellowpages.com/</gmd:URL>
                                </gmd:linkage>
                            </gmd:CI_OnlineResource>
                        </gmd:onlineResource>
                    </gmd:CI_Contact>
                </gmd:contactInfo>
                <gmd:role>
                    <gmd:CI_RoleCode codeList="http://www.isotc211.org/2005/resources/Codelist/gmxCodelists.xml#CI_RoleCode" codeListValue="pointOfContact"/>
                </gmd:role>
            </gmd:CI_ResponsibleParty>
        </gml:GenericMetaData>
    </gml:metaDataProperty>
         
    <!-- Description --> 
    <gml:description> The Typhoon VMS (Video Measuring System) is a new state of the art Tritech product. It is designed to give measurements to milimetric accuracies of any target in the camera&#x27;s field of view.
At the heart of the VMS is Tritech&#x27;s Typhoon high resolution colour zoom camera. Five red laser diodes surround the camera and up to the maximum range of the camera are clearly visible on the operators monitor.
The system software is calibrated by selecting each laser image on the display after which the software allows measurement within a few minutes of any object in the field of view.
The Typhoon VMS encompasses a 22:1 auto focus zoom lens within a 3000 m housing. Manual focus and zoom may be controlled using conventional signals or via the integrated RS232 interface.
The importance of a high quality view port is commonly overlooked in underwater cameras. The acrylic view port used on Tritech cameras has similar refractive properties to water enabling the use of a plano-concave view port, which is the preferred type of lens for deep water applications.
This view port design reduces the effects of refraction and also removes chromatic aberrations, resulting in a camera that provides a clear and sharp picture during close proximity viewing. This is absolutely essential for accurate subsea metrology.   </gml:description>
    <!-- Name --> 
    <gml:name >   Typhoon VMS   </gml:name>  
  <!-- keywords--> 
    <sml:keywords>
        <sml:KeywordList>
            <sml:keyword>marine</sml:keyword>
        </sml:KeywordList>
    </sml:keywords>

    
    <!-- Identification--> 
   
   <sml:identification>
        <sml:IdentifierList>
            <sml:identifier>
                <sml:Term definition="http://www.ifremer.fr/tematres/vocab/index.php?tema=66">
                    <sml:label>uuid</sml:label>
                    <sml:value>306c99cf-ad30-3b59-aadc-d44e305ad7e9</sml:value>
                </sml:Term>
            </sml:identifier>
        </sml:IdentifierList>
    </sml:identification>
    
    <!-- Classification -->
       
    <sml:classification>
        <sml:ClassifierList>
      
                
            <sml:classifier>
              
                <sml:Term>
                    <sml:label>model</sml:label>
                    
                    <sml:value>Typhoon VMS</sml:value>
                </sml:Term>
              
            </sml:classifier>
                
            <sml:classifier>
              
                <sml:Term definition="http://www.ifremer.fr/tematres/vocab/index.php?tema=52">
                    <sml:label>manufacturer</sml:label>
                    <sml:codeSpace xlink:href="http://www.ifremer.fr/tematres/vocab/xml.php?skosTema=40"/>
                    <sml:value>Tritech International Ltd.</sml:value>
                </sml:Term>
              
            </sml:classifier>
                
            <sml:classifier>
              
                <sml:Term>
                    <sml:label>Type</sml:label>
                    
                    <sml:value></sml:value>
                </sml:Term>
              
            </sml:classifier>
                
            <sml:classifier>
              
                <sml:Term>
                    <sml:label>Wavelength</sml:label>
                    
                    <sml:value></sml:value>
                </sml:Term>
              
            </sml:classifier>
                
            <sml:classifier>
              
                <sml:Term>
                    <sml:label>Laser power</sml:label>
                    
                    <sml:value></sml:value>
                </sml:Term>
              
            </sml:classifier>
                
            <sml:classifier>
              
                <sml:Term>
                    <sml:label>Power requirement</sml:label>
                    
                    <sml:value></sml:value>
                </sml:Term>
              
            </sml:classifier>
                
            <sml:classifier>
              
                <sml:Term>
                    <sml:label>Optical port</sml:label>
                    
                    <sml:value></sml:value>
                </sml:Term>
              
            </sml:classifier>
                
            <sml:classifier>
              
                <sml:Term>
                    <sml:label>Connector</sml:label>
                    
                    <sml:value></sml:value>
                </sml:Term>
              
            </sml:classifier>
                
            <sml:classifier>
              
                <sml:Term>
                    <sml:label>Depth</sml:label>
                    
                    <sml:value></sml:value>
                </sml:Term>
              
            </sml:classifier>
                
            <sml:classifier>
              
                <sml:Term>
                    <sml:label>Temperature</sml:label>
                    
                    <sml:value></sml:value>
                </sml:Term>
              
            </sml:classifier>
                
            <sml:classifier>
              
                <sml:Term>
                    <sml:label>Dimensions</sml:label>
                    
                    <sml:value></sml:value>
                </sml:Term>
              
            </sml:classifier>
                
            <sml:classifier>
              
                <sml:Term>
                    <sml:label>Weight in air</sml:label>
                    
                    <sml:value></sml:value>
                </sml:Term>
              
            </sml:classifier>
                
            <sml:classifier>
              
                <sml:Term>
                    <sml:label>Weight in water</sml:label>
                    
                    <sml:value></sml:value>
                </sml:Term>
              
            </sml:classifier>
                
            <sml:classifier>
              
                <sml:Term>
                    <sml:label>Materials</sml:label>
                    
                    <sml:value></sml:value>
                </sml:Term>
              
            </sml:classifier>
              
          
        </sml:ClassifierList>
    </sml:classification>
  
     <sml:documentation>
        <sml:DocumentList>         
            <sml:document>
                <gmd:CI_OnlineResource>
                    <gmd:linkage>
                        <gmd:URL>http://isi.ifremer.fr/snanny-portal/webgraphiceditorDemo/images/models/typhoon_vms.png</gmd:URL>
                    </gmd:linkage>
                    <gmd:name>
                        <gco:CharacterString>typhoon_vms.png</gco:CharacterString>
                    </gmd:name>                   
                    <gmd:function><gmd:CI_OnLineFunctionCode codeList="http://www.ifremer.fr/tematres/vocab/index.php?tema=99" codeListValue="quicklook"></gmd:CI_OnLineFunctionCode></gmd:function>
                </gmd:CI_OnlineResource>
            </sml:document>
        </sml:DocumentList>
    </sml:documentation>
   
     
     
     
   
    
</sml:PhysicalSystem>
